pytest_testit_parametrize/__init__.py
pytest_testit_parametrize/constants.py
pytest_testit_parametrize/listener.py
pytest_testit_parametrize/logger.py
pytest_testit_parametrize/plugin.py
pytest_testit_parametrize/client/__init__.py
pytest_testit_parametrize/client/api_client.py
pytest_testit_parametrize/services/__init__.py
pytest_testit_parametrize/services/parameter_manager.py
pytest_testit_parametrize/services/plugin_manager.py
pytest_testit_parametrize-0.1.5.dist-info/LICENSE
pytest_testit_parametrize-0.1.5.dist-info/METADATA
pytest_testit_parametrize-0.1.5.dist-info/WHEEL
pytest_testit_parametrize-0.1.5.dist-info/entry_points.txt
pytest_testit_parametrize-0.1.5.dist-info/top_level.txt
pytest_testit_parametrize-0.1.5.dist-info/RECORD
