Metadata-Version: 2.1
Name: pytest-testit-parametrize
Version: 0.1.5
Summary: A pytest plugin for uploading parameterized tests parameters into TMS TestIT
Author-email: Ilya Romanchenko <iromanchenko@it-vis.tech>
Maintainer-email: Ilya Romanchenko <iromanchenko@it-vis.tech>
License: 
Project-URL: Repository, https://github.com/iromanchenko-cyrm/pytest-testit-parametrize
Classifier: Framework :: Pytest
Classifier: Development Status :: 4 - Beta
Classifier: Intended Audience :: Developers
Classifier: Topic :: Software Development :: Testing
Classifier: Operating System :: OS Independent
Classifier: Programming Language :: Python
Classifier: Programming Language :: Python :: 3.9
Classifier: Programming Language :: Python :: 3.10
Classifier: Programming Language :: Python :: 3.11
Classifier: Programming Language :: Python :: 3.12
Classifier: Programming Language :: Python :: 3 :: Only
Classifier: Programming Language :: Python :: Implementation :: CPython
Classifier: License :: OSI Approved :: Apache Software License
Requires-Python: >=3.9
License-File: LICENSE
Requires-Dist: pytest>=8.3.3
Requires-Dist: testit-python-commons==3.2.6
